analysis_plot_lib/__init__.py
analysis_plot_lib/analysis_plot.py
analysis_plot_lib-0.2.1.dist-info/licenses/LICENSE
analysis_plot_lib-0.2.1.dist-info/METADATA
analysis_plot_lib-0.2.1.dist-info/WHEEL
analysis_plot_lib-0.2.1.dist-info/top_level.txt
analysis_plot_lib-0.2.1.dist-info/RECORD
