Metadata-Version: 2.4
Name: analysis_plot_lib
Version: 0.2.1
Summary: This is a simple Python package for creating pie chart.
Home-page: 
Author: Vamshi
Author-email:  X23289635@student.ncirl.ie
License: MIT
Keywords: analysis_plot_lib
Classifier: Intended Audience :: Education
Classifier: Operating System :: Microsoft :: Windows :: Windows 10
Classifier: Programming Language :: Python :: 3
Requires-Python: >=3.6
License-File: LICENSE
Dynamic: author
Dynamic: author-email
Dynamic: classifier
Dynamic: description
Dynamic: keywords
Dynamic: license
Dynamic: license-file
Dynamic: requires-python
Dynamic: summary
